Metadata-Version: 1.0
Name: mostavate
Version: 3.5.3
Summary: a Python module to motivate you
Home-page: UNKNOWN
Author: UNKNOWN
Author-email: UNKNOWN
License: UNKNOWN
Platform: UNKNOWN
